dagstd/__init__.py
dagstd/env.py
dagstd/utils.py
dagstd/constants/__init__.py
dagstd/constants/constant.py
dagstd/constants/numbers.py
dagstd/operations/__init__.py
dagstd/operations/maths.py
dagstd/operations/strings.py
dagstd/sphinx/__init__.py
dagstd/sphinx/parser.py
tests/__init__.py
tests/test_constants.py
tests/test_env.py
tests/test_operations.py
tests/test_utils.py
tests/testing_repo.py
dagstd-0.1.3.dist-info/LICENSE
dagstd-0.1.3.dist-info/METADATA
dagstd-0.1.3.dist-info/WHEEL
dagstd-0.1.3.dist-info/top_level.txt
dagstd-0.1.3.dist-info/RECORD
