Metadata-Version: 2.1
Name: dagstd
Version: 0.1.3
Summary: Dagstd
Home-page: UNKNOWN
Author: Isaac Harris-Holt
Author-email: isaac@harris-holt.com
License: GNU GPLv3
Keywords: dagster,data processing
Platform: UNKNOWN
Classifier: Intended Audience :: Developers
Classifier: Programming Language :: Python :: 3
Classifier: Operating System :: MacOS :: MacOS X
Classifier: Operating System :: Microsoft :: Windows
Requires-Python: >=3.8
License-File: LICENSE
Requires-Dist: dagster (>=0.14.17)
